README.rst
setup.py
rumple/__init__.py
rumple/container.py
rumple/decorators.py
rumple.egg-info/PKG-INFO
rumple.egg-info/SOURCES.txt
rumple.egg-info/dependency_links.txt
rumple.egg-info/top_level.txt