Metadata-Version: 1.0
Name: rumple
Version: 0.1.0
Summary: A simple dependency injection container
Home-page: https://github.com/Kilte/rumple
Author: Kilte Leichnam
Author-email: nwotnbm@gmail.com
License: MIT
Keywords: container,dependency injection,inversion of control
Platform: UNKNOWN
